{
    "id": "root",
    "isroot": true,
    "title": "vocabulary_common",
    "collapsed": false,
    "children": [
        {
            "id": "line_0",
            "title": "common",
            "background-color": "#fff",
            "collapsed": false,
            "children": [
                {
                    "id": "line_1",
                    "title": "increment",
                    "background-color": "#e3aba7",
                    "collapsed": false
                },
                {
                    "id": "line_2",
                    "title": "simplicity",
                    "background-color": "#e3aba7",
                    "collapsed": false
                },
                {
                    "id": "line_3",
                    "title": "external",
                    "background-color": "#e3aba7",
                    "collapsed": false
                },
                {
                    "id": "line_4",
                    "title": "improperly",
                    "background-color": "#e3aba7",
                    "collapsed": false
                },
                {
                    "id": "line_5",
                    "title": "highly",
                    "background-color": "#e3aba7",
                    "collapsed": false
                },
                {
                    "id": "line_6",
                    "title": "excellent",
                    "background-color": "#e3aba7",
                    "collapsed": false
                },
                {
                    "id": "line_7",
                    "title": "improperly",
                    "background-color": "#e3aba7",
                    "collapsed": false
                },
                {
                    "id": "line_8",
                    "title": "sternly",
                    "background-color": "#e3aba7",
                    "collapsed": false
                },
                {
                    "id": "line_10",
                    "title": "pertaining to",
                    "background-color": "#e3aba7",
                    "collapsed": false
                }
            ]
        }
    ]
}