[
    {"id":"root", "isroot":true, "topic":"Probability & Statistics"},
    {"id":"sub1", "parentid":"root", "topic":"Basic", "background-color":"#0000ff"},
    {"id":"sub11", "parentid":"sub1", "topic":"Basic Term"},
    {"id":"sub12", "parentid":"sub1", "topic":"Sample Space"},
    {"id":"sub13", "parentid":"sub1", "topic":"Random Varibles"},
	{"id":"sub14", "parentid":"sub1", "topic":"Probability Distribution"},
	{"id":"sub15", "parentid":"sub1", "topic":"Independent"},
	{"id":"sub16", "parentid":"sub1", "topic":"Conjucate"},	
    {"id":"sub2", "parentid":"root", "topic":"Baysian","foreground-color":"#33ff33"},
    {"id":"sub3", "parentid":"root", "topic":"Model"},
	{"id":"sub31", "parentid":"sub3", "topic":"Discriminative"},
	{"id":"sub311", "parentid":"sub31", "topic":"Linear Regression"},
    {"id":"sub32", "parentid":"sub3", "topic":"Generative"},
    {"id":"sub321", "parentid":"sub32", "topic":"Unsupervised"},
	{"id":"sub3211", "parentid":"sub321", "topic":"VAE"},
	{"id":"sub3212", "parentid":"sub321", "topic":"GAN"},
    {"id":"sub322", "parentid":"sub32", "topic":"Supervised"},	
    {"id":"sub4", "parentid":"root", "topic":"Sampling"},
	{"id":"sub5", "parentid":"root", "topic":"Information Theroy"}	
]