{
    "id": "root",
    "isroot": true,
    "title": "travis",
    "collapsed": false,
    "children": [
        {
            "id": "line_0",
            "title": "travis",
            "background-color": "#fff",
            "collapsed": false,
            "children": [
                {
                    "id": "line_1",
                    "title": "egg",
                    "background-color": "#e3aba7",
                    "collapsed": false,
                    "children": [
                        {
                            "id": "line_2",
                            "title": "github repo-badges",
                            "background-color": "#e82ad2",
                            "collapsed": false,
                            "children": [
                                {
                                    "id": "line_3",
                                    "title": "build passing",
                                    "background-color": "#0fbdff",
                                    "collapsed": false
                                },
                                {
                                    "id": "line_4",
                                    "title": "converage",
                                    "background-color": "#0fbdff",
                                    "collapsed": false
                                },
                                {
                                    "id": "line_5",
                                    "title": "etc",
                                    "background-color": "#0fbdff",
                                    "collapsed": false
                                }
                            ]
                        }
                    ]
                },
                {
                    "id": "line_6",
                    "title": "login",
                    "background-color": "#e3aba7",
                    "collapsed": false,
                    "children": [
                        {
                            "id": "line_7",
                            "title": "github",
                            "background-color": "#e82ad2",
                            "collapsed": false
                        }
                    ]
                },
                {
                    "id": "line_8",
                    "title": "using",
                    "background-color": "#e3aba7",
                    "collapsed": false,
                    "children": [
                        {
                            "id": "line_9",
                            "title": "active your github Repository",
                            "background-color": "#e82ad2",
                            "collapsed": false
                        },
                        {
                            "id": "line_10",
                            "title": ".travis.yml",
                            "background-color": "#e82ad2",
                            "collapsed": false,
                            "children": [
                                {
                                    "id": "line_11",
                                    "title": "language: nodejs",
                                    "background-color": "#0fbdff",
                                    "collapsed": false
                                },
                                {
                                    "id": "line_12",
                                    "title": "node_js:",
                                    "background-color": "#0fbdff",
                                    "collapsed": false,
                                    "children": [
                                        {
                                            "id": "line_13",
                                            "title": "- \"6\"",
                                            "background-color": "#e3aba7",
                                            "collapsed": true
                                        },
                                        {
                                            "id": "line_14",
                                            "title": "- \"8\"",
                                            "background-color": "#e3aba7",
                                            "collapsed": true
                                        }
                                    ]
                                },
                                {
                                    "id": "line_15",
                                    "title": "brancher:",
                                    "background-color": "#0fbdff",
                                    "collapsed": false,
                                    "children": [
                                        {
                                            "id": "line_16",
                                            "title": "only:",
                                            "background-color": "#e3aba7",
                                            "collapsed": true,
                                            "children": [
                                                {
                                                    "id": "line_17",
                                                    "title": "- \"dev\"",
                                                    "background-color": "#d41dea",
                                                    "collapsed": true
                                                },
                                                {
                                                    "id": "line_18",
                                                    "title": "- \"master\"",
                                                    "background-color": "#d41dea",
                                                    "collapsed": true
                                                }
                                            ]
                                        }
                                    ]
                                },
                                {
                                    "id": "line_19",
                                    "title": "install",
                                    "background-color": "#0fbdff",
                                    "collapsed": false,
                                    "children": [
                                        {
                                            "id": "line_20",
                                            "title": "- \"npm install\"",
                                            "background-color": "#e3aba7",
                                            "collapsed": true
                                        },
                                        {
                                            "id": "line_21",
                                            "title": "- \"npm install -g codecov\"",
                                            "background-color": "#e3aba7",
                                            "collapsed": true
                                        }
                                    ]
                                },
                                {
                                    "id": "line_22",
                                    "title": "script:",
                                    "background-color": "#0fbdff",
                                    "collapsed": false,
                                    "children": [
                                        {
                                            "id": "line_23",
                                            "title": "- \"npm run cover\"",
                                            "background-color": "#e3aba7",
                                            "collapsed": true
                                        },
                                        {
                                            "id": "line_24",
                                            "title": "- \"codecov\"",
                                            "background-color": "#e3aba7",
                                            "collapsed": true
                                        }
                                    ]
                                }
                            ]
                        },
                        {
                            "id": "line_25",
                            "title": "commit",
                            "background-color": "#e82ad2",
                            "collapsed": false,
                            "children": [
                                {
                                    "id": "line_26",
                                    "title": "auto CI",
                                    "background-color": "#0fbdff",
                                    "collapsed": false
                                }
                            ]
                        },
                        {
                            "id": "line_27",
                            "title": "debug",
                            "background-color": "#e82ad2",
                            "collapsed": false,
                            "children": [
                                {
                                    "id": "line_28",
                                    "title": "show job log",
                                    "background-color": "#0fbdff",
                                    "collapsed": false
                                }
                            ]
                        },
                        {
                            "id": "line_29",
                            "title": "coverge info",
                            "background-color": "#e82ad2",
                            "collapsed": false,
                            "children": [
                                {
                                    "id": "line_30",
                                    "title": "codecov.io",
                                    "background-color": "#0fbdff",
                                    "collapsed": false
                                },
                                {
                                    "id": "line_31",
                                    "title": "install",
                                    "background-color": "#0fbdff",
                                    "collapsed": false,
                                    "children": [
                                        {
                                            "id": "line_32",
                                            "title": "npm install -g codecov",
                                            "background-color": "#e3aba7",
                                            "collapsed": true
                                        }
                                    ]
                                }
                            ]
                        }
                    ]
                }
            ]
        }
    ]
}